hJson/__init__.py
py_hJson-1.0.0.dist-info/METADATA
py_hJson-1.0.0.dist-info/WHEEL
py_hJson-1.0.0.dist-info/top_level.txt
py_hJson-1.0.0.dist-info/RECORD
